quicksave/__init__.py
quicksave/backup_manager.py
quicksave/cli.py
quicksave/config.py
quicksave/version.py
quicksave_tool-0.1.1.dist-info/licenses/LICENSE
quicksave_tool-0.1.1.dist-info/METADATA
quicksave_tool-0.1.1.dist-info/WHEEL
quicksave_tool-0.1.1.dist-info/entry_points.txt
quicksave_tool-0.1.1.dist-info/top_level.txt
quicksave_tool-0.1.1.dist-info/RECORD
