Metadata-Version: 2.4
Name: quicksave-tool
Version: 0.1.1
Summary: A command line tool for saving snapshots of game saves
Author: Mathias Staricka
Classifier: Development Status :: 3 - Alpha
Classifier: Programming Language :: Python :: 3
Classifier: License :: OSI Approved :: MIT License
Classifier: Operating System :: OS Independent
Requires-Python: >=3.13
License-File: LICENSE
Requires-Dist: argparse>=1.4.0
Requires-Dist: boto3>=1.38.30
Requires-Dist: pyyaml>=6.0.2
Dynamic: license-file
